LICENSE
README.md
setup.py
pyprosegur/__init__.py
pyprosegur/auth.py
pyprosegur/exceptions.py
pyprosegur/installation.py
pyprosegur.egg-info/PKG-INFO
pyprosegur.egg-info/SOURCES.txt
pyprosegur.egg-info/dependency_links.txt
pyprosegur.egg-info/entry_points.txt
pyprosegur.egg-info/requires.txt
pyprosegur.egg-info/top_level.txt
pyprosegur.egg-info/zip-safe