Metadata-Version: 2.1
Name: pyprosegur
Version: 0.0.8
Summary: Unofficial Python library to interface with Prosegur Alarmes PT/ES.
Home-page: https://github.com/dgomes/pyprosegur
Author: Diogo Gomes
Author-email: diogogomes@gmail.com
License: MIT License
Platform: any
Classifier: License :: OSI Approved :: MIT License
Classifier: Intended Audience :: Developers
Classifier: Operating System :: OS Independent
Classifier: Programming Language :: Python
Classifier: Programming Language :: Python :: 3
Classifier: Topic :: Software Development :: Libraries :: Python Modules
License-File: LICENSE
